{
	"name": "ds_raw_results_data",
	"properties": {
		"linkedServiceName": {
			"referenceName": "ls_datalake",
			"type": "LinkedServiceReference"
		},
		"folder": {
			"name": "results datasets"
		},
		"annotations": [],
		"type": "DelimitedText",
		"typeProperties": {
			"location": {
				"type": "AzureBlobFSLocation",
				"fileName": "results.csv",
				"folderPath": "raw",
				"fileSystem": "rawdata"
			},
			"columnDelimiter": ",",
			"escapeChar": "\\",
			"firstRowAsHeader": true,
			"quoteChar": "\""
		},
		"schema": [
			{
				"name": "resultId",
				"type": "String"
			},
			{
				"name": "raceId",
				"type": "String"
			},
			{
				"name": "driverId",
				"type": "String"
			},
			{
				"name": "constructorId",
				"type": "String"
			},
			{
				"name": "number",
				"type": "String"
			},
			{
				"name": "grid",
				"type": "String"
			},
			{
				"name": "position",
				"type": "String"
			},
			{
				"name": "positionText",
				"type": "String"
			},
			{
				"name": "positionOrder",
				"type": "String"
			},
			{
				"name": "points",
				"type": "String"
			},
			{
				"name": "laps",
				"type": "String"
			},
			{
				"name": "time",
				"type": "String"
			},
			{
				"name": "milliseconds",
				"type": "String"
			},
			{
				"name": "fastestLap",
				"type": "String"
			},
			{
				"name": "rank",
				"type": "String"
			},
			{
				"name": "fastestLapTime",
				"type": "String"
			},
			{
				"name": "fastestLapSpeed",
				"type": "String"
			},
			{
				"name": "statusId",
				"type": "String"
			}
		]
	},
	"type": "Microsoft.DataFactory/factories/datasets"
}